podcast_scraper/__init__.py
podcast_scraper/cli.py
podcast_scraper/france_culture.py
podcast_scraper/generic_parser.py
podcast_scraper/monde_diplo.py
podcast_scraper-0.1.0.dist-info/METADATA
podcast_scraper-0.1.0.dist-info/WHEEL
podcast_scraper-0.1.0.dist-info/entry_points.txt
podcast_scraper-0.1.0.dist-info/top_level.txt
podcast_scraper-0.1.0.dist-info/RECORD
